<?xml version='1.0' encoding="UTF-8"?>
<Defs xmlns:xsd="http://www.w3.org/2001/XMLSchema" xmlns:xsi="http://www.w3.org/2001/XMLSchema-instance">

  	<DataDef entityType="TileObject" xsi:type="FNEEntityData">
		<id>to_tricrane_crate_stack</id>
		<pathingCost>150</pathingCost>
		<seeThrough>true</seeThrough>
		<editorName>Crate (Stack)</editorName>
		<smallCollisionBox>false</smallCollisionBox>
		<blocking>true</blocking>
		<editorCategoryName>Tricrane</editorCategoryName>
		<entityViewVariations>
			<viewRef>to_tricrane_crate_stack_view</viewRef>
		</entityViewVariations>
	</DataDef>

    <DataDef xsi:type="FNEEntityViewData">
		<id>to_tricrane_crate_stack_view</id>
		<viewIsGameObject>false</viewIsGameObject>
		<entityMeshData>mesh_tricrane_crate_stack_view</entityMeshData>
		<scaleMod>1.18</scaleMod>
	</DataDef>

</Defs>