<?xml version='1.0' encoding="UTF-8"?>
<Defs xmlns:xsd="http://www.w3.org/2001/XMLSchema" xmlns:xsi="http://www.w3.org/2001/XMLSchema-instance">

    <DataDef xsi:type="TileData">
		<id>grass</id>
		<category>nature</category>
		<albedopath>Data/XML/World/Tile/TileMaps/Mudplains/Grass/MudPlains_DefaultMaterial_BaseMap.png</albedopath>
		<maskmappath>Data/XML/World/Tile/TileMaps/Mudplains/Grass/MudPlains_DefaultMaterial_MaskMap.png</maskmappath>
		<normalpath>Data/XML/World/Tile/TileMaps/Mudplains/Grass/MudPlains_DefaultMaterial_Normal.png</normalpath>
		<overlapPriority>10</overlapPriority>
		<hardEdges>false</hardEdges>
		<mapColor>#55aa55</mapColor>
		<chanceToSpawnTileObject>10</chanceToSpawnTileObject>
		<tileObjectGenDataList>	
			<TileObjectGenData>
				<objectRef>to_potato_plant</objectRef>
				<weight>50</weight>
			</TileObjectGenData>

			<TileObjectGenData>
				<objectRef>to_cotton_wild</objectRef>
				<weight>100</weight>
			</TileObjectGenData>

			<TileObjectGenData>
				<objectRef>to_biome_1_tree_a</objectRef>
				<weight>500</weight>
				<tileObjectGenClusterData>
					<radius>2</radius>
					<density>5</density>
				</tileObjectGenClusterData>
			</TileObjectGenData>
			
			<TileObjectGenData>
				<objectRef>to_biome_1_tree_a_large</objectRef>
				<weight>300</weight>
				<tileObjectGenClusterData>
					<radius>3</radius>
					<density>3</density>
				</tileObjectGenClusterData>
			</TileObjectGenData>
			
			<TileObjectGenData>
				<objectRef>to_biome_1_tree_b</objectRef>
				<weight>400</weight>
				<tileObjectGenClusterData>
					<radius>4</radius>
					<density>10</density>
				</tileObjectGenClusterData>
			</TileObjectGenData>

			<TileObjectGenData>
				<objectRef>to_krystberry_bush_wild</objectRef>
				<weight>30</weight>
			</TileObjectGenData>
		</tileObjectGenDataList>
		<atmosphereRef>mud_plains_atmosphere</atmosphereRef>
	</DataDef>

	<DataDef xsi:type="TileData">
		<id>grassy_dirt</id>
		<category>nature</category>
		<albedopath>Data/XML/World/Tile/TileMaps/Mudplains/GrassyDirt/MudPlains_DefaultMaterial_BaseMap.png</albedopath>
		<maskmappath>Data/XML/World/Tile/TileMaps/Mudplains/GrassyDirt/MudPlains_DefaultMaterial_MaskMap.png</maskmappath>
		<normalpath>Data/XML/World/Tile/TileMaps/Mudplains/GrassyDirt/MudPlains_DefaultMaterial_Normal.png</normalpath>
		<overlapPriority>9</overlapPriority>
		<hardEdges>false</hardEdges>
		<mapColor>#88aa66</mapColor>
		<chanceToSpawnTileObject>5</chanceToSpawnTileObject>
		<tileObjectGenDataList>
			
			<TileObjectGenData>
				<objectRef>to_biome_1_tree_a</objectRef>
				<weight>400</weight>
			</TileObjectGenData>

			<TileObjectGenData>
				<objectRef>to_biome_1_tree_b</objectRef>
				<weight>300</weight>
			</TileObjectGenData>

			<TileObjectGenData>
				<objectRef>to_cotton_wild</objectRef>
				<weight>125</weight>
			</TileObjectGenData>

			<TileObjectGenData>
				<objectRef>to_biome_1_rock_large</objectRef>
				<weight>500</weight>
			</TileObjectGenData>

			<TileObjectGenData>
				<objectRef>to_potato_plant</objectRef>
				<weight>100</weight>
			</TileObjectGenData>

			<TileObjectGenData>
				<objectRef>to_krystberry_bush_wild</objectRef>
				<weight>150</weight>
			</TileObjectGenData>

			<TileObjectGenData>
				<objectRef>to_crashed_robot</objectRef>
				<weight>10</weight>
			</TileObjectGenData>
		</tileObjectGenDataList>
		<timeEffectFrequency>100</timeEffectFrequency>
		<atmosphereRef>mud_plains_atmosphere</atmosphereRef>
	</DataDef>

	<DataDef xsi:type="TileData">
		<id>dirt</id>
		<category>nature</category>
		<albedopath>Data/XML/World/Tile/TileMaps/Mudplains/Dirt/MudPlains_DefaultMaterial_BaseMap.png</albedopath>
		<maskmappath>Data/XML/World/Tile/TileMaps/Mudplains/Dirt/MudPlains_DefaultMaterial_MaskMap.png</maskmappath>
		<normalpath>Data/XML/World/Tile/TileMaps/Mudplains/Dirt/MudPlains_DefaultMaterial_Normal.png</normalpath>
		<overlapPriority>8</overlapPriority>
		<mapColor>#886644</mapColor>
		<hardEdges>false</hardEdges>
		<chanceToSpawnTileObject>5</chanceToSpawnTileObject>
		<tileObjectGenDataList>

			<TileObjectGenData>
				<objectRef>to_biome_1_rock_large</objectRef>
				<weight>800</weight>
			</TileObjectGenData>

			<TileObjectGenData>
				<objectRef>to_biome_1_rock_large</objectRef>
				<weight>400</weight>
			</TileObjectGenData>
			
			<TileObjectGenData>
				<objectRef>to_biome_1_tree_b</objectRef>
				<weight>300</weight>
			</TileObjectGenData>

			<TileObjectGenData>
				<objectRef>to_big_iron_rock_1</objectRef>
				<weight>10</weight>
				<tileObjectGenClusterData>
					<radius>3</radius>
					<density>25</density>
				</tileObjectGenClusterData>
			</TileObjectGenData>
			
			<TileObjectGenData>
				<objectRef>to_cotton_wild</objectRef>
				<weight>125</weight>
			</TileObjectGenData>

			<TileObjectGenData>
				<objectRef>to_crashed_pod</objectRef>
				<weight>5</weight>
			</TileObjectGenData>

			<TileObjectGenData>
				<objectRef>to_crashed_robot</objectRef>
				<weight>25</weight>
			</TileObjectGenData>

		</tileObjectGenDataList>
		<timeEffectFrequency>100</timeEffectFrequency>
		<atmosphereRef>mud_plains_atmosphere</atmosphereRef>
	</DataDef>

	<DataDef xsi:type="TileData">
		<id>muddy_dirt</id>
		<category>nature</category>
		<albedopath>Data/XML/World/Tile/TileMaps/Mudplains/MuddyDirt/MudPlains_DefaultMaterial_BaseMap.png</albedopath>
		<maskmappath>Data/XML/World/Tile/TileMaps/Mudplains/MuddyDirt/MudPlains_DefaultMaterial_MaskMap.png</maskmappath>
		<normalpath>Data/XML/World/Tile/TileMaps/Mudplains/MuddyDirt/MudPlains_DefaultMaterial_Normal.png</normalpath>
		<overlapPriority>7</overlapPriority>
		<mapColor>#775533</mapColor>
		<hardEdges>false</hardEdges>
		<chanceToSpawnTileObject>8</chanceToSpawnTileObject>
		<tileObjectGenDataList>
			<TileObjectGenData>
				<objectRef>to_biome_1_rock_large</objectRef>
				<weight>1000</weight>
			</TileObjectGenData>

			<TileObjectGenData>
				<objectRef>to_biome_1_rock_large</objectRef>
				<weight>500</weight>
			</TileObjectGenData>

			<TileObjectGenData>
				<objectRef>to_big_iron_rock_1</objectRef>
				<weight>200</weight>
			</TileObjectGenData>

			<TileObjectGenData>
				<objectRef>to_potato_plant</objectRef>
				<weight>100</weight>
			</TileObjectGenData>

			<TileObjectGenData>
				<objectRef>to_crashed_pod</objectRef>
				<weight>20</weight>
			</TileObjectGenData>

			<TileObjectGenData>
				<objectRef>to_crashed_robot</objectRef>
				<weight>10</weight>
			</TileObjectGenData>

		</tileObjectGenDataList>
		<timeEffectFrequency>5</timeEffectFrequency>
		<atmosphereRef>mud_plains_atmosphere</atmosphereRef>
	</DataDef>

	<DataDef xsi:type="TileData">
		<id>mud</id>
		<category>nature</category>
		<albedopath>Data/XML/World/Tile/TileMaps/Mudplains/Mud/MudPlains_DefaultMaterial_BaseMap.png</albedopath>
		<maskmappath>Data/XML/World/Tile/TileMaps/Mudplains/Mud/MudPlains_DefaultMaterial_MaskMap.png</maskmappath>
		<normalpath>Data/XML/World/Tile/TileMaps/Mudplains/Mud/MudPlains_DefaultMaterial_Normal.png</normalpath>
		<overlapPriority>6</overlapPriority>
		<hardEdges>false</hardEdges>
		<mapColor>#554422</mapColor>
		<chanceToSpawnTileObject>5</chanceToSpawnTileObject>
		<tileObjectGenDataList>
			<TileObjectGenData>
				<objectRef>to_biome_1_rock_large</objectRef>
				<weight>500</weight>
			</TileObjectGenData>

			<TileObjectGenData>
				<objectRef>to_crashed_pod</objectRef>
				<weight>10</weight>
			</TileObjectGenData>

			<TileObjectGenData>
				<objectRef>to_crashed_robot</objectRef>
				<weight>40</weight>
			</TileObjectGenData>
		</tileObjectGenDataList>
		<atmosphereRef>mud_plains_atmosphere</atmosphereRef>
	</DataDef>

	<DataDef xsi:type="TileData">
		<id>water_tile</id>
		<category>nature</category>
		<overlapPriority>1000000</overlapPriority>
		<hardEdges>true</hardEdges>
		<mapColor>#444499</mapColor>
		<isWater>true</isWater>
		<isBlocking>true</isBlocking>
		<WaterTileData>
			<edgeMeshRef>water_edge</edgeMeshRef>
			<tileHeightOffset>-0.2</tileHeightOffset>
		</WaterTileData>
	</DataDef>
</Defs>